Workbook

Sheet Narrative Shocks_READ ME
A1: Data Explanation
A2: See paper and on-line appendix for sources and further details: https://www.bankofcanada.ca/wp-content/uploads/2021/08/swp2021-41.pdf
A4: Abbreviation | C4: Meaning | D4: Definition
A5: DATES | C5: date | D5: Year.Quarter (00=Q1, .25=Q2 etc.)
A6: T_PI | C6: Narratively identified shock to personal income taxes | D6: Change in federal personal income tax liabilities divided by lagged taxable personal income
A7: T_CI | C7: Narratively identified shock to corporate income taxes | D7: Change in federal corporate income tax liabilities divided by lagged taxable corporate income
A8: m_PI | C8: Proxy for shocks to personal income taxes | D8: T_PI where non-zero observations have been subtracted their mean
A9: m_CI | C9: Proxy for shocks to corporate income taxes | D9: T_CI where non-zero observations have been subtracted their mean
A10: APITR | C10: Average personal income tax rate | D10: Federal personal income tax revenues including contributions to government social insurance divided by personal income tax base
A11: ACITR | C11: Average Corporate income tax rate | D11: Federal corporate income tax reveneues divided by coporate income tax base

Sheet Narrative Shocks (Quarterly)
A1: DATES | B1: Narrative PI Shocks (T_PI, right axis) | C1: Narrative CI Shocks (T_CI, right axis) | D1: m_PI Narratively identified shock to personal income taxes where non-zero observations have been subtracted their mean ( -0.2482) | E1: m_CI Narratively identified shock to corporate income taxes where non-zero observations have been subtracted their mean (-0.8734) | F1: APITR | G1: Average Tax Rate (left axis) | H1: ACITR | I1: Average Tax Rate (left axis) | J1: T_PI original from Mertens and Ravn (2013, AER) | K1: T_CI original from Mertens and Ravn (2013, AER) | L1: m_PI original from Mertens and Ravn (2013, AER) | M1: m_CI original from Mertens and Ravn (2013, AER) | N1: APITR original from Mertens and Ravn (2013, AER) | O1: ACITR original from Mertens and Ravn (2013, AER)
A2: 1950 | B2: 0 | C2: 0 | D2: 0 | E2: 0 | F2: =DATA!E2 -> 0.12842557 | G2: =F2*100 -> 12.842557 | H2: =DATA!F2 -> 0.32498655 | I2: =H2*100 -> 32.498655 | J2: 0 | K2: 0 | L2: 0 | M2: 0 | N2: 0.098162476 | O2: 0.43581081
A3: =A2+0.25 -> 1950.25 | B3: 0 | C3: 0 | D3: 0 | E3: 0 | F3: =DATA!E3 -> 0.12793591 | G3: =F3*100 -> 12.793591 | H3: =DATA!F3 -> 0.32512315 | I3: =H3*100 -> 32.512315 | J3: 0 | K3: 0 | L3: 0 | M3: 0 | N3: 0.09901915 | O3: 0.46385542
A4: =A3+0.25 -> 1950.5 | B4: 0 | C4: 0 | D4: 0 | E4: 0 | F4: =DATA!E4 -> 0.11979693 | G4: =F4*100 -> 11.979693 | H4: =DATA!F4 -> 0.32421376 | I4: =H4*100 -> 32.421376 | J4: 0 | K4: 0 | L4: 0 | M4: 0 | N4: 0.10035367 | O4: 0.49868074
A5: =A4+0.25 -> 1950.75 | B5: 0 | C5: 0 | D5: 0 | E5: 0 | F5: =DATA!E5 -> 0.1215654 | G5: =F5*100 -> 12.15654 | H5: =DATA!F5 -> 0.32353545 | I5: =H5*100 -> 32.353545 | J5: 0 | K5: 0 | L5: 0 | M5: 0 | N5: 0.11285532 | O5: 0.50364964
A6: =A5+0.25 -> 1951 | B6: 0 | C6: 0 | D6: 0 | E6: 0 | F6: =DATA!E6 -> 0.11963602 | G6: =F6*100 -> 11.963602 | H6: =DATA!F6 -> 0.31756511 | I6: =H6*100 -> 31.756511 | J6: 0 | K6: 0 | L6: 0 | M6: 0 | N6: 0.11889251 | O6: 0.625
A7: =A6+0.25 -> 1951.25 | B7: 0 | C7: 0 | D7: 0 | E7: 0 | F7: =DATA!E7 -> 0.10452225 | G7: =F7*100 -> 10.452225 | H7: =DATA!F7 -> 0.31807178 | I7: =H7*100 -> 31.807178 | J7: 0 | K7: 0 | L7: 0 | M7: 0 | N7: 0.12341772 | O7: 0.52882206
A8: =A7+0.25 -> 1951.5 | B8: 0 | C8: 0 | D8: 0 | E8: 0 | F8: =DATA!E8 -> 0.098793596 | G8: =F8*100 -> 9.8793596 | H8: =DATA!F8 -> 0.3173246 | I8: =H8*100 -> 31.73246 | J8: 0 | K8: 0 | L8: 0 | M8: 0 | N8: 0.12676056 | O8: 0.47277228
A9: =A8+0.25 -> 1951.75 | B9: 0 | C9: 0 | D9: 0 | E9: 0 | F9: =DATA!E9 -> 0.098944984 | G9: =F9*100 -> 9.8944984 | H9: =DATA!F9 -> 0.31630824 | I9: =H9*100 -> 31.630824 | J9: 0 | K9: 0 | L9: 0 | M9: 0 | N9: 0.13136729 | O9: 0.48803828
A10: =A9+0.25 -> 1952 | B10: 0 | C10: 0 | D10: 0 | E10: 0 | F10: =DATA!E10 -> 0.10115884 | G10: =F10*100 -> 10.115884 | H10: =DATA!F10 -> 0.31304776 | I10: =H10*100 -> 31.304776 | J10: 0 | K10: 0 | L10: 0 | M10: 0 | N10: 0.13581184 | O10: 0.47704082
A11: =A10+0.25 -> 1952.25 | B11: 0 | C11: 0 | D11: 0 | E11: 0 | F11: =DATA!E11 -> 0.097294172 | G11: =F11*100 -> 9.7294172 | H11: =DATA!F11 -> 0.31172452 | I11: =H11*100 -> 31.172452 | J11: 0 | K11: 0 | L11: 0 | M11: 0 | N11: 0.1369248 | O11: 0.47439353
A12: =A11+0.25 -> 1952.5 | B12: 0 | C12: 0 | D12: 0 | E12: 0 | F12: =DATA!E12 -> 0.092827846 | G12: =F12*100 -> 9.2827846 | H12: =DATA!F12 -> 0.31379403 | I12: =H12*100 -> 31.379403 | J12: 0 | K12: 0 | L12: 0 | M12: 0 | N12: 0.13538236 | O12: 0.47554348
A13: =A12+0.25 -> 1952.75 | B13: 0 | C13: 0 | D13: 0 | E13: 0 | F13: =DATA!E13 -> 0.089062989 | G13: =F13*100 -> 8.9062989 | H13: =DATA!F13 -> 0.31364492 | I13: =H13*100 -> 31.364492 | J13: 0 | K13: 0 | L13: 0 | M13: 0 | N13: 0.13600573 | O13: 0.47188264
A14: =A13+0.25 -> 1953 | B14: 0 | C14: 0 | D14: 0 | E14: 0 | F14: =DATA!E14 -> 0.089483917 | G14: =F14*100 -> 8.9483917 | H14: =DATA!F14 -> 0.38402485 | I14: =H14*100 -> 38.402485 | J14: 0 | K14: 0 | L14: 0 | M14: 0 | N14: 0.13481169 | O14: 0.49038462
... A229: =A228+0.25 -> 2006.75 | B229: 0 | C229: 0 | D229: 0 | E229: 0 | F229: =DATA!E229 -> 0.16045696 | G229: =F229*100 -> 16.045696 | H229: =DATA!F229 -> 0.18947295 | I229: =H229*100 -> 18.947295 | J229: 0 | K229: 0 | L229: 0 | M229: 0 | N229: 0.18549036 | O229: 0.22808259
A230: =A229+0.25 -> 2007 | B230: 0 | C230: 0 | D230: 0 | E230: 0 | F230: =DATA!E230 -> 0.15920634 | G230: =F230*100 -> 15.920634 | H230: =DATA!F230 -> 0.17730948 | I230: =H230*100 -> 17.730948
A231: =A230+0.25 -> 2007.25 | B231: 0 | C231: 0 | D231: 0 | E231: 0 | F231: =DATA!E231 -> 0.1598276 | G231: =F231*100 -> 15.98276 | H231: =DATA!F231 -> 0.18233498 | I231: =H231*100 -> 18.233498
A232: =A231+0.25 -> 2007.5 | B232: 0 | C232: 0 | D232: 0 | E232: 0 | F232: =DATA!E232 -> 0.16139396 | G232: =F232*100 -> 16.139396 | H232: =DATA!F232 -> 0.18762021 | I232: =H232*100 -> 18.762021
A233: =A232+0.25 -> 2007.75 | B233: 0 | C233: 0 | D233: 0 | E233: 0 | F233: =DATA!E233 -> 0.15975747 | G233: =F233*100 -> 15.975747 | H233: =DATA!F233 -> 0.19040587 | I233: =H233*100 -> 19.040587
A234: =A233+0.25 -> 2008 | B234: 0 | C234: 0 | D234: 0 | E234: 0 | F234: =DATA!E234 -> 0.16777375 | G234: =F234*100 -> 16.777375 | H234: =DATA!F234 -> 0.19651659 | I234: =H234*100 -> 19.651659
A235: =A234+0.25 -> 2008.25 | B235: 0 | C235: 0 | D235: 0 | E235: 0 | F235: =DATA!E235 -> 0.16803071 | G235: =F235*100 -> 16.803071 | H235: =DATA!F235 -> 0.1893296 | I235: =H235*100 -> 18.93296
A236: =A235+0.25 -> 2008.5 | B236: 0 | C236: 0 | D236: 0 | E236: 0 | F236: =DATA!E236 -> 0.16887626 | G236: =F236*100 -> 16.887626 | H236: =DATA!F236 -> 0.18708696 | I236: =H236*100 -> 18.708696
A237: =A236+0.25 -> 2008.75 | B237: 0 | C237: 0 | D237: 0 | E237: 0 | F237: =DATA!E237 -> 0.16891366 | G237: =F237*100 -> 16.891366 | H237: =DATA!F237 -> 0.19445869 | I237: =H237*100 -> 19.445869
A238: =A237+0.25 -> 2009 | B238: 0 | C238: 0 | D238: 0 | E238: 0 | F238: =DATA!E238 -> 0.17135974 | G238: =F238*100 -> 17.135974 | H238: =DATA!F238 -> 0.19742861 | I238: =H238*100 -> 19.742861
A239: =A238+0.25 -> 2009.25 | B239: 0 | C239: 0 | D239: 0 | E239: 0 | F239: =DATA!E239 -> 0.17090179 | G239: =F239*100 -> 17.090179 | H239: =DATA!F239 -> 0.19768962 | I239: =H239*100 -> 19.768962
A240: =A239+0.25 -> 2009.5 | B240: 0 | C240: 0 | D240: 0 | E240: 0 | F240: =DATA!E240 -> 0.17161258 | G240: =F240*100 -> 17.161258 | H240: =DATA!F240 -> 0.20294861 | I240: =H240*100 -> 20.294861
A241: =A240+0.25 -> 2009.75 | B241: 0 | C241: 0 | D241: 0 | E241: 0 | F241: =DATA!E241 -> 0.173648 | G241: =F241*100 -> 17.3648 | H241: =DATA!F241 -> 0.19550986 | I241: =H241*100 -> 19.550986
... A279: =A278+0.25 -> 2019.25 | B279: 0 | C279: 0 | D279: 0 | E279: 0 | F279: =DATA!E279 -> 0.17173915 | G279: =F279*100 -> 17.173915 | H279: =DATA!F279 -> 0.14749227 | I279: =H279*100 -> 14.749227
A280: 2019.5 | B280: 0 | C280: 0 | D280: 0 | E280: 0 | F280: =DATA!E280 -> 0.17188731 | G280: =F280*100 -> 17.188731 | H280: =DATA!F280 -> 0.15049883 | I280: =H280*100 -> 15.049883
A281: 2019.75 | B281: 0 | C281: 0 | D281: 0 | E281: 0 | F281: =DATA!E281 -> 0.17226475 | G281: =F281*100 -> 17.226475 | H281: =DATA!F281 -> 0.13689893 | I281: =H281*100 -> 13.689893
B284: correlation between PI and CI up to 2006
B285: =CORREL(B2:B229,C2:C229) -> 0.47911218
B286: correlation between PI and CI up to 2019
B287: =CORREL(B2:B281,C2:C281) -> 0.50008012

Sheet DATA
B1: Gross Domestic Product Billions of Dollars, Quarterly, Seasonally Adjusted Annual Rate https://fred.stlouisfed.org/series/GDP | C1: Corporate profits before tax (without IVA and CCAdj), Billions of Dollars, Quarterly, Seasonally Adjusted Annual Rate https://fred.stlouisfed.org/series/A053RC1Q027SBEA | D1: Personal taxable income defined as personal income - government transfers + contributions for government social insurance | E1: APITR (personal current taxes + contributions for government social insurance)/personal taxable income | F1: ACITR taxes on corporate profits/corporate profits | G1: Personal Income Billions of Dollars, Quarterly, Seasonally Adjusted Annual Rate https://fred.stlouisfed.org/series/PINCOME | H1: Transfer payments Government social benefits: to persons, Billions of Dollars, Quarterly, Seasonally Adjusted Annual Rate; NIPA table 3.2 line 28 | I1: Personal current taxes NIPA table 3.2 line 3 | J1: Contributions to social insurance from persons, Billions of dollars, seasonally adjusted at annual rates; NIPA table 3.2 line 11 | K1: Taxes on Corporate Income NIPA table 3.2 line 8
A2: 17168 | B2: 243.164 | C2: 33.466 | D2: 189.713 | E2: =(I2+J2)/D2 -> 0.12842557 | F2: =K2/C2 -> 0.32498655 | G2: 189.713 | H2: 7.712 | I2: 18.192 | J2: 6.172 | K2: 10.876
A3: 17258 | B3: 245.968 | C3: 31.668 | D3: 189.72 | E3: =(I3+J3)/D3 -> 0.12793591 | F3: =K3/C3 -> 0.32512315 | G3: 189.72 | H3: 7.296 | I3: 18.488 | J3: 5.784 | K3: 10.296
A4: 17349 | B4: 249.585 | C4: 31.288 | D4: 197.768 | E4: =(I4+J4)/D4 -> 0.11979693 | F4: =K4/C4 -> 0.32421376 | G4: 197.768 | H4: 10.68 | I4: 18.704 | J4: 4.988 | K4: 10.144
A5: 17441 | B5: 259.745 | C5: 34.123 | D5: 200.715 | E5: =(I5+J5)/D5 -> 0.1215654 | F5: =K5/C5 -> 0.32353545 | G5: 200.715 | H5: 7.844 | I5: 19.788 | J5: 4.612 | K5: 11.04
A6: 17533 | B6: 265.742 | C6: 35.747 | D6: 206.493 | E6: =(I6+J6)/D6 -> 0.11963602 | F6: =K6/C6 -> 0.31756511 | G6: 206.493 | H6: 7.472 | I6: 20.06 | J6: 4.644 | K6: 11.352
A7: 17624 | B7: 272.567 | C7: 37.589 | D7: 211.974 | E7: =(I7+J7)/D7 -> 0.10452225 | F7: =K7/C7 -> 0.31807178 | G7: 211.974 | H7: 7.244 | I7: 17.808 | J7: 4.348 | K7: 11.956
A8: 17715 | B8: 279.196 | C8: 36.959 | D8: 217.423 | E8: =(I8+J8)/D8 -> 0.098793596 | F8: =K8/C8 -> 0.3173246 | G8: 217.423 | H8: 7 | I8: 17.1 | J8: 4.38 | K8: 11.728
A9: 17807 | B9: 280.366 | C9: 35.712 | D9: 218.101 | E9: =(I9+J9)/D9 -> 0.098944984 | F9: =K9/C9 -> 0.31630824 | G9: 218.101 | H9: 7.028 | I9: 17.292 | J9: 4.288 | K9: 11.296
A10: 17899 | B10: 275.034 | C10: 32.519 | D10: 212.023 | E10: =(I10+J10)/D10 -> 0.10115884 | F10: =K10/C10 -> 0.31304776 | G10: 212.023 | H10: 7.676 | I10: 16.472 | J10: 4.976 | K10: 10.18
A11: 17989 | B11: 271.351 | C11: 28.692 | D11: 210.989 | E11: =(I11+J11)/D11 -> 0.097294172 | F11: =K11/C11 -> 0.31172452 | G11: 210.989 | H11: 8.152 | I11: 15.648 | J11: 4.88 | K11: 8.944
A12: 18080 | B12: 272.889 | C12: 29.752 | D12: 210.411 | E12: =(I12+J12)/D12 -> 0.092827846 | F12: =K12/C12 -> 0.31379403 | G12: 210.411 | H12: 8.472 | I12: 14.932 | J12: 4.6 | K12: 9.336
A13: 18172 | B13: 270.627 | C13: 29.205 | D13: 210.862 | E13: =(I13+J13)/D13 -> 0.089062989 | F13: =K13/C13 -> 0.31364492 | G13: 210.862 | H13: 8.5 | I13: 14.452 | J13: 4.328 | K13: 9.16
... A293: 43739 | B293: 21694.458 | C293: 2279.536 | D293: 18648.499 | E293: =(I293+J293)/D293 -> 0.16890619 | F293: =K293/C293 -> 0.10153163 | G293: 18648.499 | H293: 2350.8 | I293: 1728.574 | J293: 1421.273 | K293: 231.445
